deadline/nuke_adaptor/__init__.py
deadline/nuke_adaptor/_version.py
deadline/nuke_adaptor/NukeAdaptor/NukeAdaptor.json
deadline/nuke_adaptor/NukeAdaptor/__init__.py
deadline/nuke_adaptor/NukeAdaptor/__main__.py
deadline/nuke_adaptor/NukeAdaptor/adaptor.py
deadline/nuke_adaptor/NukeAdaptor/py.typed
deadline/nuke_adaptor/NukeAdaptor/schemas/init_data.schema.json
deadline/nuke_adaptor/NukeAdaptor/schemas/run_data.schema.json
deadline/nuke_adaptor/NukeClient/__init__.py
deadline/nuke_adaptor/NukeClient/nuke_client.py
deadline/nuke_adaptor/NukeClient/nuke_handler.py
deadline/nuke_adaptor/NukeClient/py.typed
deadline/nuke_submitter/__init__.py
deadline/nuke_submitter/_logging.py
deadline/nuke_submitter/_version.py
deadline/nuke_submitter/adaptor_override_environment.yaml
deadline/nuke_submitter/assets.py
deadline/nuke_submitter/copycat_adaptor.py
deadline/nuke_submitter/copycat_job_template.yaml
deadline/nuke_submitter/data_classes.py
deadline/nuke_submitter/deadline_submitter_for_nuke.py
deadline/nuke_submitter/default_nuke_job_template.yaml
deadline/nuke_submitter/job_bundle_output_test_runner.py
deadline/nuke_submitter/py.typed
deadline/nuke_submitter/ui/__init__.py
deadline/nuke_submitter/ui/components/__init__.py
deadline/nuke_submitter/ui/components/asset_scan_warning_dialog.py
deadline/nuke_submitter/ui/components/scene_settings_tab.py
deadline/nuke_util/__init__.py
deadline/nuke_util/_version.py
deadline/nuke_util/ocio.py
deadline_cloud_for_nuke-0.18.16.dist-info/METADATA
deadline_cloud_for_nuke-0.18.16.dist-info/WHEEL
deadline_cloud_for_nuke-0.18.16.dist-info/entry_points.txt
deadline_cloud_for_nuke-0.18.16.dist-info/licenses/LICENSE
deadline_cloud_for_nuke-0.18.16.dist-info/licenses/NOTICE
deadline_cloud_for_nuke-0.18.16.dist-info/RECORD
